{
  "display": {
    "icon": {
      "item": "ma:ice_crystal"
    },
    "title": {
      "translate": "advancements.ice_crystal_obtaining.title"
    },
    "description": {
      "translate": "advancements.ice_crystal_obtaining.descr"
    },
    "frame": "task",
    "show_toast": true,
    "announce_to_chat": true,
    "hidden": false
  },
  "criteria": {
    "ice_crystal_obtaining": {
      "trigger": "minecraft:inventory_changed",
      "conditions": {
        "items": [
          {
            "items": [
              "ma:ice_crystal"
            ],
            "count": {
              "min": 1,
              "max": 1
            }
          }
        ]
      }
    }
  },
  "parent": "ma:ice_soul_obtaining"
}